<?xml version="1.0" encoding="utf-8"?>
<xd:acceleratorMap xmlns:xd="http://www.xilinx.com/xidane" xd:functionName="SkipList_HeadOffs" xd:componentRef="SkipList_HeadOffs" xd:initiationInterval="109170" xd:clockPeriod="10.000000" xd:sequential="true" xd:hostMachine="64" xd:reset="control">
  <xd:controlReg xd:name="control" xd:interfaceRef="s_axi_CFG" xd:busTypeRef="axilite" xd:type="generic_axi_lite" xd:offset="0x0"/>
  <xd:arg xd:name="a-&gt;val" xd:originalName="a" xd:direction="inout" xd:interfaceRef="m_axi_A_BUS" xd:busTypeRef="aximm" xd:dataPack="true" xd:bitMapping="31:0" xd:dataWidth="32" xd:bufferDirection="in"/>
  <xd:arg xd:name="a-&gt;offs[0]" xd:originalName="a" xd:direction="inout" xd:interfaceRef="m_axi_A_BUS" xd:busTypeRef="aximm" xd:dataPack="true" xd:bitMapping="63:32" xd:dataWidth="32" xd:bufferDirection="in"/>
  <xd:arg xd:name="a-&gt;offs[1]" xd:originalName="a" xd:direction="inout" xd:interfaceRef="m_axi_A_BUS" xd:busTypeRef="aximm" xd:dataPack="true" xd:bitMapping="95:64" xd:dataWidth="32" xd:bufferDirection="in"/>
  <xd:arg xd:name="a-&gt;dummy" xd:originalName="a" xd:direction="inout" xd:interfaceRef="m_axi_A_BUS" xd:busTypeRef="aximm" xd:dataPack="true" xd:bitMapping="127:96" xd:dataWidth="32" xd:bufferDirection="in"/>
  <xd:arg xd:name="a" xd:originalName="a" xd:direction="in" xd:interfaceRef="s_axi_CFG" xd:busTypeRef="axilite" xd:aximmInterfaceRef="m_axi_A_BUS" xd:dataWidth="32" xd:offset="0x10" xd:handshakeRef="ap_none"/>
  <xd:latencyEstimates xd:best-case="109169" xd:worst-case="109169" xd:average-case="109169"/>
  <xd:resourceEstimates xd:LUT="1139" xd:FF="926" xd:BRAM="9" xd:DSP="0"/>
</xd:acceleratorMap>
